Metadata-Version: 1.0
Name: libpath
Version: 0.0.0.0
Summary: libpath, for Python
Home-page: https://github.com/synesissoftware/libpath.Python
Author: Matt Wilson
Author-email: matthew@synesis.com.au
License: BSD-3-Clause
Platform: UNKNOWN
